watertea/__init__.py
watertea/gpus.py
watertea/main.py
watertea/plots.py
watertea/results.py
watertea/utils.py
watertea-0.1.2.post5.dist-info/METADATA
watertea-0.1.2.post5.dist-info/WHEEL
watertea-0.1.2.post5.dist-info/top_level.txt
watertea-0.1.2.post5.dist-info/RECORD
