Metadata-Version: 2.4
Name: watertea
Version: 0.1.2.post5
Summary: Add your description here
Requires-Python: >=3.11
Requires-Dist: nvitop>=1.5.1
Requires-Dist: pandas>=2.2.3
Requires-Dist: pip>=25.1.1
Requires-Dist: seaborn>=0.13.2
Requires-Dist: torch>=2.7.0
